{"rows":[
     {"deliveryDo":"","id":"1","rollNumber":"JP127931001","rollName":"卷名称","rollClassify":"卷分类","nominal":"30","doorsill":"使用门槛","blockUp":"","goDate":"2016-9-10","upDate":"2016-10-11","third":"0","cooperation":"合作单位","state":"状态","remark":"备注","print":"","note":""},
     {"deliveryDo":"","id":"2","rollNumber":"JP127931002","rollName":"卷名称","rollClassify":"卷分类","nominal":"40","doorsill":"使用门槛","blockUp":"","goDate":"2016-9-10","upDate":"2016-10-11","third":"1","cooperation":"合作单位","state":"状态","remark":"备注","print":"","note":""},
     {"deliveryDo":"","id":"3","rollNumber":"JP127931003","rollName":"卷名称","rollClassify":"卷分类","nominal":"50","doorsill":"使用门槛","blockUp":"","goDate":"2016-9-10","upDate":"2016-10-11","third":"1","cooperation":"合作单位","state":"状态","remark":"备注","print":"","note":""},
     {"deliveryDo":"","id":"4","rollNumber":"JP127931004","rollName":"卷名称","rollClassify":"卷分类","nominal":"60","doorsill":"使用门槛","blockUp":"","goDate":"2016-9-10","upDate":"2016-10-11","third":"1","cooperation":"合作单位","state":"状态","remark":"备注","print":"","note":""},
     {"deliveryDo":"","id":"5","rollNumber":"JP127931005","rollName":"卷名称","rollClassify":"卷分类","nominal":"70","doorsill":"使用门槛","blockUp":"","goDate":"2016-9-10","upDate":"2016-10-11","third":"1","cooperation":"合作单位","state":"状态","remark":"备注","print":"","note":""}
]}